ska_sdc/__init__.py
ska_sdc/common/__init__.py
ska_sdc/common/models/__init__.py
ska_sdc/common/models/exceptions.py
ska_sdc/common/models/sdc_score.py
ska_sdc/common/utils/__init__.py
ska_sdc/common/utils/cat_io.py
ska_sdc/common/utils/constants.py
ska_sdc/common/utils/score_helper.py
ska_sdc/common/utils/xmatch.py
ska_sdc/data/__init__.py
ska_sdc/data/data_resources.py
ska_sdc/data/beam_info/PB_I_14.log
ska_sdc/data/conf/sdc2/config.ini
ska_sdc/sdc1/__init__.py
ska_sdc/sdc1/dc_defns.py
ska_sdc/sdc1/sdc1_scorer.py
ska_sdc/sdc1/validate.py
ska_sdc/sdc1/models/__init__.py
ska_sdc/sdc1/models/sdc1_score.py
ska_sdc/sdc1/utils/__init__.py
ska_sdc/sdc1/utils/create_score.py
ska_sdc/sdc1/utils/prep.py
ska_sdc/sdc1/utils/score_helper.py
ska_sdc/sdc1/utils/sdc1_xmatch.py
ska_sdc/sdc1/utils/sieve.py
ska_sdc/sdc2/__init__.py
ska_sdc/sdc2/sdc2_scorer.py
ska_sdc/sdc2/validate.py
ska_sdc/sdc2/models/__init__.py
ska_sdc/sdc2/models/sdc2_score.py
ska_sdc/sdc2/utils/__init__.py
ska_sdc/sdc2/utils/create_score.py
ska_sdc/sdc2/utils/score_helper.py
ska_sdc/sdc2/utils/sdc2_xmatch.py
ska_sdc/sdc2/utils/xmatch_postprocessing.py
ska_sdc/sdc2/utils/xmatch_postprocessing_steps.py
ska_sdc/sdc2/utils/xmatch_preprocessing.py
ska_sdc/sdc2/utils/xmatch_preprocessing_steps.py
ska_sdc-2.0.0.dist-info/LICENSE
ska_sdc-2.0.0.dist-info/METADATA
ska_sdc-2.0.0.dist-info/WHEEL
ska_sdc-2.0.0.dist-info/top_level.txt
ska_sdc-2.0.0.dist-info/RECORD
