Metadata-Version: 2.1
Name: ska-sdc
Version: 2.0.0
Summary: A package providing tools for the SKA Science Data Challenges.
Home-page: https://gitlab.com/ska-telescope/sdc/ska-sdc
Author: SKA Organisation
License: BSD 3-clause
Platform: UNKNOWN
Classifier: Development Status :: 4 - Beta
Classifier: License :: OSI Approved :: BSD License
Classifier: Programming Language :: Python
Classifier: Programming Language :: Python :: 3.6
Classifier: Topic :: Software Development :: Libraries
Classifier: Topic :: Software Development :: Libraries :: Python Modules
Classifier: Intended Audience :: Developers
Classifier: Intended Audience :: Science/Research
Requires-Python: >=3.6
Requires-Dist: numpy (>=1.18)
Requires-Dist: pandas (>=0.25)
Requires-Dist: scikit-learn (>=0.22)
Requires-Dist: astropy (>=4.0)
